brainminer/__init__.py
brainminer/agent/__init__.py
brainminer/agent/agent.py
brainminer/alphas/__init__.py
brainminer/alphas/alpha101.py
brainminer/brain/__init__.py
brainminer/brain/alpha.py
brainminer/brain/brain.py
brainminer/brain/evaluator.py
brainminer/brain/model.py
brainminer/brain/session.py
brainminer/brain/simulator.py
brainminer/miner/__init__.py
brainminer/miner/dbwrapper.py
brainminer/miner/miner.py
brainminer/miner/model.py
brainminer/miner/schedule.py
brainminer/miner/schema.py
brainminer/miner/tricks.py
brainminer/utils/__init__.py
brainminer/utils/rate_limiter.py
brainminer/utils/rwlock.py
brainminer/utils/utils.py
brainminer-0.1.2.dist-info/METADATA
brainminer-0.1.2.dist-info/WHEEL
brainminer-0.1.2.dist-info/RECORD
